dfx_apiv2_protos/__init__.py
dfx_apiv2_protos/analysis_pb2.py
dfx_apiv2_protos/bundles_pb2.py
dfx_apiv2_protos/devices_pb2.py
dfx_apiv2_protos/dfx_pb2.py
dfx_apiv2_protos/general_pb2.py
dfx_apiv2_protos/groups_pb2.py
dfx_apiv2_protos/measurements_pb2.py
dfx_apiv2_protos/meta_pb2.py
dfx_apiv2_protos/organizations_pb2.py
dfx_apiv2_protos/profiles_pb2.py
dfx_apiv2_protos/studies_pb2.py
dfx_apiv2_protos/users_pb2.py
dfx_apiv2_protos/util_pb2.py
dfx_apiv2_protos-2.24.0.dist-info/LICENSE.txt
dfx_apiv2_protos-2.24.0.dist-info/METADATA
dfx_apiv2_protos-2.24.0.dist-info/WHEEL
dfx_apiv2_protos-2.24.0.dist-info/top_level.txt
dfx_apiv2_protos-2.24.0.dist-info/RECORD
